Workbook

Sheet Assumptions
A1: ANM Community App — Resource & Pricing Assumptions
A3: Project | B3: ANM Community App
A4: Client | B4: ANM — Church & Community Platform
A5: Prepared by | B5: Solution Development Team
A6: Date | B6: June 2025
A7: Currency | B7: USD ($)
A8: Version | B8: v1.0 — Draft
A11: RATE CARD — Daily Rates (USD)
A12: Role | B12: Daily Rate (USD) | C12: Role ID | D12: Notes / Scope
A13: Project Manager | B13: 900 | C13: PM | D13: Sr PM; reporting, risk, ANM stakeholder comms
A14: Solution Architect | B14: 1200 | C14: ARC | D14: Architecture reviews & formal sign-off gates
A15: UI/UX Designer | B15: 800 | C15: DES | D15: Figma, design system, UAT design support
A16: Mobile Developer (Sr.) | B16: 950 | C16: MOB | D16: React Native — iOS & Android cross-platform
A17: Backend Developer (Sr.) | B17: 950 | C17: BAK | D17: Node.js / Express, MongoDB Atlas, REST APIs
A18: DevOps Engineer | B18: 850 | C18: DEV | D18: AWS ECS, CI/CD, S3/CloudFront, monitoring
A19: QA Engineer | B19: 750 | C19: QA | D19: E2E, unit, load, accessibility testing
A20: Security Consultant | B20: 1100 | C20: SEC | D20: OWASP pentest, audit & sign-off report
A23: PRICING ASSUMPTIONS
A24: Parameter | B24: Value | D24: Notes
A25: Gross Margin % (on cost) | B25: 0.5 | D25: 50% margin added on top of total cost → client price
A26: Working Days / Week | B26: 5 | D26: Mon–Fri; excludes public holidays & bank holidays
A27: Hypercare Duration (weeks) | B27: 2 | D27: Post go-live monitoring & support period
A28: Sprint Length (weeks) | B28: 2 | D28: Agile: 2-week sprint cadence (5 sprints total)
A29: Project Duration — Core (wks) | B29: 10 | D29: Wk 1 through Wk 10 (Discovery → Go-Live)
A30: Total Duration incl. HC (wks) | B30: 12 | D30: Core 10 weeks + 2 hypercare weeks
A33: COLOR CODING LEGEND
A34: Blue text | B34: (sample) | D34: Hardcoded input — users may change these for scenario analysis
A35: Black text | B35: (sample) | D35: Excel formula / calculated value — do not edit manually
A36: Green text | B36: (sample) | D36: Link pulling from another worksheet within this workbook

Sheet Resource Plan
A1: ANM Community App — Resource Loading Plan (Team-Days per Week)
A2: PHASE | B2: Phase 1: Discovery & Design | D2: Phase 2: Core Development | H2: Phase 3: QA & Testing | J2: Phase 4: Deployment | K2: Phase 5: Hypercare | N2: TOTAL | O2: FTE | P2: Phase Focus
A3: Role | B3: Wk 1 | C3: Wk 2 | D3: Wk 3 | E3: Wk 4 | F3: Wk 5 | G3: Wk 6 | H3: Wk 7 | I3: Wk 8 | J3: Wk 9 | K3: Wk 10 | L3: HC-1 | M3: HC-2 | N3: Days | O3: ÷50d | P3: Notes
A4: Project Manager | B4: 5 | C4: 5 | D4: 3 | E4: 3 | F4: 3 | G4: 3 | H4: 3 | I4: 3 | J4: 5 | K4: 4 | L4: 2 | M4: 2 | N4: =SUM(B4:M4) | O4: =N4/50 | P4: Discovery → Go-Live → Hypercare oversight
A5: Solution Architect | B5: 5 | C5: 5 | D5: 1 | E5: 1 | F5: 1 | G5: 1 | H5: 1 | I5: 1 | J5: 1 | N5: =SUM(B5:M5) | O5: =N5/50 | P5: Discovery, architecture gate & QA gate only
A6: UI/UX Designer | B6: 5 | C6: 5 | D6: 2 | E6: 2 | F6: 1 | G6: 1 | N6: =SUM(B6:M6) | O6: =N6/50 | P6: Design-heavy in Wks 1–4; wraps up Wk 6
A7: Mobile Developer (Sr.) | C7: 1 | D7: 5 | E7: 5 | F7: 5 | G7: 5 | H7: 3 | I7: 3 | J7: 4 | K7: 2 | L7: 2 | M7: 2 | N7: =SUM(B7:M7) | O7: =N7/50 | P7: Full dev sprints 2–5; bug-fix in QA & HC
A8: Backend Developer (Sr.) | B8: 2 | C8: 2 | D8: 5 | E8: 5 | F8: 5 | G8: 5 | H8: 3 | I8: 3 | J8: 3 | K8: 1 | L8: 2 | M8: 2 | N8: =SUM(B8:M8) | O8: =N8/50 | P8: API design Wks 1–2; full from Wk 3 onward
A9: DevOps Engineer | B9: 3 | C9: 3 | D9: 2 | E9: 2 | F9: 2 | G9: 2 | H9: 2 | I9: 2 | J9: 5 | K9: 4 | L9: 3 | M9: 3 | N9: =SUM(B9:M9) | O9: =N9/50 | P9: Env setup Wks 1–2; full prod deploy Wk 9
A10: QA Engineer | D10: 1 | E10: 1 | F10: 1 | G10: 1 | H10: 5 | I10: 5 | J10: 3 | K10: 1 | L10: 1 | M10: 1 | N10: =SUM(B10:M10) | O10: =N10/50 | P10: Light in dev; full engagement Wks 7–8
A11: Security Consultant | H11: 4 | I11: 4 | N11: =SUM(B11:M11) | O11: =N11/50 | P11: OWASP pentest Wks 7–8 only; written report
A12: TOTAL TEAM-DAYS / WEEK | B12: =SUM(B4:B11) | C12: =SUM(C4:C11) | D12: =SUM(D4:D11) | E12: =SUM(E4:E11) | F12: =SUM(F4:F11) | G12: =SUM(G4:G11) | H12: =SUM(H4:H11) | I12: =SUM(I4:I11) | ... N12: =SUM(N4:N11)
A13: Max capacity (8 roles × 5d) | B13: 40 | C13: 40 | D13: 40 | E13: 40 | F13: 40 | G13: 40 | H13: 40 | I13: 40 | J13: 40 | K13: 40 | L13: 40 | M13: 40 | N13: =SUM(B13:M13)
A14: Utilisation % | B14: =IFERROR(B12/B13,"-") | C14: =IFERROR(C12/C13,"-") | D14: =IFERROR(D12/D13,"-") | E14: =IFERROR(E12/E13,"-") | F14: =IFERROR(F12/F13,"-") | G14: =IFERROR(G12/G13,"-") | H14: =IFERROR(H12/H13,"-") | I14: =IFERROR(I12/I13,"-") | ... M14: =IFERROR(M12/M13,"-")
A17: PHASE SUMMARY
A18: Phase | B18: Weeks | C18: Team-Days | D18: % of Total | E18: Avg daily headcount
A19: Phase 1: Discovery & Design | B19: Wks 1–2 | C19: =SUM(B12:C12) | D19: =IFERROR(C19/C24,"-") | E19: =IFERROR(ROUND(C19/(2*5),1),"-")
A20: Phase 2: Core Development | B20: Wks 3–6 | C20: =SUM(D12:G12) | D20: =IFERROR(C20/C24,"-") | E20: =IFERROR(ROUND(C20/(4*5),1),"-")
A21: Phase 3: QA & Testing | B21: Wks 7–8 | C21: =SUM(H12:I12) | D21: =IFERROR(C21/C24,"-") | E21: =IFERROR(ROUND(C21/(2*5),1),"-")
A22: Phase 4: Deployment | B22: Wk 9 | C22: =J12 | D22: =IFERROR(C22/C24,"-") | E22: =IFERROR(ROUND(C22/(1*5),1),"-")
A23: Phase 5: Hypercare (Wk10+HC) | B23: Wks 10–12 | C23: =SUM(K12:M12) | D23: =IFERROR(C23/C24,"-") | E23: =IFERROR(ROUND(C23/(3*5),1),"-")
A24: TOTAL | B24: 12 wks | C24: =SUM(B12:M12) | D24: =IFERROR(C24/C24,"-") | E24: =IFERROR(ROUND(C24/(12*5),1),"-")

Sheet Cost Model
A1: ANM Community App — Cost Build-up & Pricing Model
A2: Green = cross-sheet link · Blue = editable input · Black = formula · Margin applied in rows 14–17 · Amounts in USD
A3: Role | B3: Daily Rate (USD) | C3: Project Days (Wks 1–10) | D3: HC Days (2 wks) | E3: Total Days | F3: Project Cost (USD) | G3: HC Cost (USD) | H3: Total Cost (USD) | I3: % of Total | J3: Source / Notes
A4: Project Manager | B4: =Assumptions!B13 | C4: =SUM('Resource Plan'!B4:K4) | D4: =SUM('Resource Plan'!L4:M4) | E4: =C4+D4 | F4: =B4*C4 | G4: =B4*D4 | H4: =F4+G4 | I4: =IFERROR(H4/H12,0) | J4: Source: Assumptions!B13 | Days: Resource Plan rows 4, cols B:K and L:M
A5: Solution Architect | B5: =Assumptions!B14 | C5: =SUM('Resource Plan'!B5:K5) | D5: =SUM('Resource Plan'!L5:M5) | E5: =C5+D5 | F5: =B5*C5 | G5: =B5*D5 | H5: =F5+G5 | I5: =IFERROR(H5/H12,0) | J5: Source: Assumptions!B14 | Primarily Wks 1–2; gates in later phases
A6: UI/UX Designer | B6: =Assumptions!B15 | C6: =SUM('Resource Plan'!B6:K6) | D6: =SUM('Resource Plan'!L6:M6) | E6: =C6+D6 | F6: =B6*C6 | G6: =B6*D6 | H6: =F6+G6 | I6: =IFERROR(H6/H12,0) | J6: Source: Assumptions!B15 | Design-heavy Wks 1–4; wraps by Wk 6
A7: Mobile Developer (Sr.) | B7: =Assumptions!B16 | C7: =SUM('Resource Plan'!B7:K7) | D7: =SUM('Resource Plan'!L7:M7) | E7: =C7+D7 | F7: =B7*C7 | G7: =B7*D7 | H7: =F7+G7 | I7: =IFERROR(H7/H12,0) | J7: Source: Assumptions!B16 | Full sprints Wks 3–8; part-time in HC
A8: Backend Developer (Sr.) | B8: =Assumptions!B17 | C8: =SUM('Resource Plan'!B8:K8) | D8: =SUM('Resource Plan'!L8:M8) | E8: =C8+D8 | F8: =B8*C8 | G8: =B8*D8 | H8: =F8+G8 | I8: =IFERROR(H8/H12,0) | J8: Source: Assumptions!B17 | Full sprints Wks 3–8; part-time in HC
A9: DevOps Engineer | B9: =Assumptions!B18 | C9: =SUM('Resource Plan'!B9:K9) | D9: =SUM('Resource Plan'!L9:M9) | E9: =C9+D9 | F9: =B9*C9 | G9: =B9*D9 | H9: =F9+G9 | I9: =IFERROR(H9/H12,0) | J9: Source: Assumptions!B18 | Env setup Wks 1–2; full deployment Wk 9
A10: QA Engineer | B10: =Assumptions!B19 | C10: =SUM('Resource Plan'!B10:K10) | D10: =SUM('Resource Plan'!L10:M10) | E10: =C10+D10 | F10: =B10*C10 | G10: =B10*D10 | H10: =F10+G10 | I10: =IFERROR(H10/H12,0) | J10: Source: Assumptions!B19 | Full engagement Wks 7–8 QA phase
A11: Security Consultant | B11: =Assumptions!B20 | C11: =SUM('Resource Plan'!B11:K11) | D11: =SUM('Resource Plan'!L11:M11) | E11: =C11+D11 | F11: =B11*C11 | G11: =B11*D11 | H11: =F11+G11 | I11: =IFERROR(H11/H12,0) | J11: Source: Assumptions!B20 | OWASP pentest Wks 7–8 only; fixed scope
A12: TOTAL COST (before margin) | C12: =SUM(C4:C11) | D12: =SUM(D4:D11) | E12: =SUM(E4:E11) | F12: =SUM(F4:F11) | G12: =SUM(G4:G11) | H12: =SUM(H4:H11) | I12: 100.0%
A14: Total Cost (USD) | H14: =H12
A15: Gross Margin % (50%) | H15: =Assumptions!B25
A16: Margin Amount (USD) | H16: =H14*H15
A17: TOTAL CLIENT PRICE (USD) | H17: =H14+H16
A19: COST & PRICE BY DELIVERY PHASE
A20: Phase | B20: Weeks | C20: Team-Days | D20: Proportional Cost (USD) | E20: Selling Price incl. 50% Margin | F20: % of Total Price
A21: Phase 1: Discovery & Design | B21: Wks 1–2 | C21: =SUM('Resource Plan'!B12:C12) | D21: =IFERROR(C21/E12*H12,0) | E21: =IFERROR(D21*(1+Assumptions!B25),0) | F21: =IFERROR(E21/H17,"-")
A22: Phase 2: Core Development | B22: Wks 3–6 | C22: =SUM('Resource Plan'!D12:G12) | D22: =IFERROR(C22/E12*H12,0) | E22: =IFERROR(D22*(1+Assumptions!B25),0) | F22: =IFERROR(E22/H17,"-")
A23: Phase 3: QA & Testing | B23: Wks 7–8 | C23: =SUM('Resource Plan'!H12:I12) | D23: =IFERROR(C23/E12*H12,0) | E23: =IFERROR(D23*(1+Assumptions!B25),0) | F23: =IFERROR(E23/H17,"-")
A24: Phase 4: Deployment | B24: Wk 9 | C24: ='Resource Plan'!J12 | D24: =IFERROR(C24/E12*H12,0) | E24: =IFERROR(D24*(1+Assumptions!B25),0) | F24: =IFERROR(E24/H17,"-")
A25: Phase 5: Hypercare (Wk10+HC) | B25: Wks 10–12 | C25: =SUM('Resource Plan'!K12:M12) | D25: =IFERROR(C25/E12*H12,0) | E25: =IFERROR(D25*(1+Assumptions!B25),0) | F25: =IFERROR(E25/H17,"-")
A26: TOTAL | B26: 12 wks | C26: =E12 | D26: =IFERROR(C26/E12*H12,0) | E26: =IFERROR(D26*(1+Assumptions!B25),0) | F26: =IFERROR(E26/H17,"-")

Sheet Weekly Cost
A1: ANM Community App — Weekly Cost Breakdown & Cash Flow
A2: Costs = days (Resource Plan) × rate (Assumptions) · Selling price = cost × (1 + 50% margin) · Amounts in USD
A3: Week | B3: Phase | C3: PM | D3: Architect | E3: Designer | F3: Mobile Dev | G3: Backend Dev | H3: DevOps | I3: QA | J3: Security | K3: Total Cost /Wk (USD) | L3: Cumul. Cost (USD) | M3: Sell Price /Wk (USD) | N3: Cumul. Sell Price (USD)
A4: Wk 1 | B4: Phase 1: Discovery & Design | C4: ='Resource Plan'!B4*Assumptions!B13 | D4: ='Resource Plan'!B5*Assumptions!B14 | E4: ='Resource Plan'!B6*Assumptions!B15 | F4: ='Resource Plan'!B7*Assumptions!B16 | G4: ='Resource Plan'!B8*Assumptions!B17 | H4: ='Resource Plan'!B9*Assumptions!B18 | I4: ='Resource Plan'!B10*Assumptions!B19 | J4: ='Resource Plan'!B11*Assumptions!B20 | K4: =SUM(C4:J4) | L4: =K4 | M4: =K4*(1+Assumptions!B25) | N4: =M4
A5: Wk 2 | B5: Phase 1: Discovery & Design | C5: ='Resource Plan'!C4*Assumptions!B13 | D5: ='Resource Plan'!C5*Assumptions!B14 | E5: ='Resource Plan'!C6*Assumptions!B15 | F5: ='Resource Plan'!C7*Assumptions!B16 | G5: ='Resource Plan'!C8*Assumptions!B17 | H5: ='Resource Plan'!C9*Assumptions!B18 | I5: ='Resource Plan'!C10*Assumptions!B19 | J5: ='Resource Plan'!C11*Assumptions!B20 | K5: =SUM(C5:J5) | L5: =L4+K5 | M5: =K5*(1+Assumptions!B25) | N5: =N4+M5
A6: Wk 3 | B6: Phase 2: Core Development | C6: ='Resource Plan'!D4*Assumptions!B13 | D6: ='Resource Plan'!D5*Assumptions!B14 | E6: ='Resource Plan'!D6*Assumptions!B15 | F6: ='Resource Plan'!D7*Assumptions!B16 | G6: ='Resource Plan'!D8*Assumptions!B17 | H6: ='Resource Plan'!D9*Assumptions!B18 | I6: ='Resource Plan'!D10*Assumptions!B19 | J6: ='Resource Plan'!D11*Assumptions!B20 | K6: =SUM(C6:J6) | L6: =L5+K6 | M6: =K6*(1+Assumptions!B25) | N6: =N5+M6
A7: Wk 4 | B7: Phase 2: Core Development | C7: ='Resource Plan'!E4*Assumptions!B13 | D7: ='Resource Plan'!E5*Assumptions!B14 | E7: ='Resource Plan'!E6*Assumptions!B15 | F7: ='Resource Plan'!E7*Assumptions!B16 | G7: ='Resource Plan'!E8*Assumptions!B17 | H7: ='Resource Plan'!E9*Assumptions!B18 | I7: ='Resource Plan'!E10*Assumptions!B19 | J7: ='Resource Plan'!E11*Assumptions!B20 | K7: =SUM(C7:J7) | L7: =L6+K7 | M7: =K7*(1+Assumptions!B25) | N7: =N6+M7
A8: Wk 5 | B8: Phase 2: Core Development | C8: ='Resource Plan'!F4*Assumptions!B13 | D8: ='Resource Plan'!F5*Assumptions!B14 | E8: ='Resource Plan'!F6*Assumptions!B15 | F8: ='Resource Plan'!F7*Assumptions!B16 | G8: ='Resource Plan'!F8*Assumptions!B17 | H8: ='Resource Plan'!F9*Assumptions!B18 | I8: ='Resource Plan'!F10*Assumptions!B19 | J8: ='Resource Plan'!F11*Assumptions!B20 | K8: =SUM(C8:J8) | L8: =L7+K8 | M8: =K8*(1+Assumptions!B25) | N8: =N7+M8
A9: Wk 6 | B9: Phase 2: Core Development | C9: ='Resource Plan'!G4*Assumptions!B13 | D9: ='Resource Plan'!G5*Assumptions!B14 | E9: ='Resource Plan'!G6*Assumptions!B15 | F9: ='Resource Plan'!G7*Assumptions!B16 | G9: ='Resource Plan'!G8*Assumptions!B17 | H9: ='Resource Plan'!G9*Assumptions!B18 | I9: ='Resource Plan'!G10*Assumptions!B19 | J9: ='Resource Plan'!G11*Assumptions!B20 | K9: =SUM(C9:J9) | L9: =L8+K9 | M9: =K9*(1+Assumptions!B25) | N9: =N8+M9
A10: Wk 7 | B10: Phase 3: QA & Testing | C10: ='Resource Plan'!H4*Assumptions!B13 | D10: ='Resource Plan'!H5*Assumptions!B14 | E10: ='Resource Plan'!H6*Assumptions!B15 | F10: ='Resource Plan'!H7*Assumptions!B16 | G10: ='Resource Plan'!H8*Assumptions!B17 | H10: ='Resource Plan'!H9*Assumptions!B18 | I10: ='Resource Plan'!H10*Assumptions!B19 | J10: ='Resource Plan'!H11*Assumptions!B20 | K10: =SUM(C10:J10) | L10: =L9+K10 | M10: =K10*(1+Assumptions!B25) | N10: =N9+M10
A11: Wk 8 | B11: Phase 3: QA & Testing | C11: ='Resource Plan'!I4*Assumptions!B13 | D11: ='Resource Plan'!I5*Assumptions!B14 | E11: ='Resource Plan'!I6*Assumptions!B15 | F11: ='Resource Plan'!I7*Assumptions!B16 | G11: ='Resource Plan'!I8*Assumptions!B17 | H11: ='Resource Plan'!I9*Assumptions!B18 | I11: ='Resource Plan'!I10*Assumptions!B19 | J11: ='Resource Plan'!I11*Assumptions!B20 | K11: =SUM(C11:J11) | L11: =L10+K11 | M11: =K11*(1+Assumptions!B25) | N11: =N10+M11
A12: Wk 9 | B12: Phase 4: Deployment | C12: ='Resource Plan'!J4*Assumptions!B13 | D12: ='Resource Plan'!J5*Assumptions!B14 | E12: ='Resource Plan'!J6*Assumptions!B15 | F12: ='Resource Plan'!J7*Assumptions!B16 | G12: ='Resource Plan'!J8*Assumptions!B17 | H12: ='Resource Plan'!J9*Assumptions!B18 | I12: ='Resource Plan'!J10*Assumptions!B19 | J12: ='Resource Plan'!J11*Assumptions!B20 | K12: =SUM(C12:J12) | L12: =L11+K12 | M12: =K12*(1+Assumptions!B25) | N12: =N11+M12
A13: Wk 10 | B13: Phase 5: Hypercare | C13: ='Resource Plan'!K4*Assumptions!B13 | D13: ='Resource Plan'!K5*Assumptions!B14 | E13: ='Resource Plan'!K6*Assumptions!B15 | F13: ='Resource Plan'!K7*Assumptions!B16 | G13: ='Resource Plan'!K8*Assumptions!B17 | H13: ='Resource Plan'!K9*Assumptions!B18 | I13: ='Resource Plan'!K10*Assumptions!B19 | J13: ='Resource Plan'!K11*Assumptions!B20 | K13: =SUM(C13:J13) | L13: =L12+K13 | M13: =K13*(1+Assumptions!B25) | N13: =N12+M13
A14: HC-Wk1 | B14: Phase 5: Hypercare | C14: ='Resource Plan'!L4*Assumptions!B13 | D14: ='Resource Plan'!L5*Assumptions!B14 | E14: ='Resource Plan'!L6*Assumptions!B15 | F14: ='Resource Plan'!L7*Assumptions!B16 | G14: ='Resource Plan'!L8*Assumptions!B17 | H14: ='Resource Plan'!L9*Assumptions!B18 | I14: ='Resource Plan'!L10*Assumptions!B19 | J14: ='Resource Plan'!L11*Assumptions!B20 | K14: =SUM(C14:J14) | L14: =L13+K14 | M14: =K14*(1+Assumptions!B25) | N14: =N13+M14
A15: HC-Wk2 | B15: Phase 5: Hypercare | C15: ='Resource Plan'!M4*Assumptions!B13 | D15: ='Resource Plan'!M5*Assumptions!B14 | E15: ='Resource Plan'!M6*Assumptions!B15 | F15: ='Resource Plan'!M7*Assumptions!B16 | G15: ='Resource Plan'!M8*Assumptions!B17 | H15: ='Resource Plan'!M9*Assumptions!B18 | I15: ='Resource Plan'!M10*Assumptions!B19 | J15: ='Resource Plan'!M11*Assumptions!B20 | K15: =SUM(C15:J15) | L15: =L14+K15 | M15: =K15*(1+Assumptions!B25) | N15: =N14+M15
A16: TOTAL | C16: =SUM(C4:C15) | D16: =SUM(D4:D15) | E16: =SUM(E4:E15) | F16: =SUM(F4:F15) | G16: =SUM(G4:G15) | H16: =SUM(H4:H15) | I16: =SUM(I4:I15) | J16: =SUM(J4:J15) | K16: =SUM(K4:K15) | L16: =L15 | M16: =SUM(M4:M15) | N16: =N15
A19: COST SUMMARY BY PHASE
A20: Phase | B20: Weeks | C20: Team-Days | D20: Cost (USD) | E20: Selling Price (USD) | F20: % of Total
A21: Phase 1: Discovery & Design | B21: Wks 1–2 | C21: =SUM('Resource Plan'!B12:C12) | D21: =SUM(K4:K5) | E21: =SUM(M4:M5) | F21: =IFERROR(E21/E26,"-")
A22: Phase 2: Core Development | B22: Wks 3–6 | C22: =SUM('Resource Plan'!D12:G12) | D22: =SUM(K6:K9) | E22: =SUM(M6:M9) | F22: =IFERROR(E22/E26,"-")
A23: Phase 3: QA & Testing | B23: Wks 7–8 | C23: =SUM('Resource Plan'!H12:I12) | D23: =SUM(K10:K11) | E23: =SUM(M10:M11) | F23: =IFERROR(E23/E26,"-")
A24: Phase 4: Deployment | B24: Wk 9 | C24: ='Resource Plan'!J12 | D24: =SUM(K12) | E24: =SUM(M12) | F24: =IFERROR(E24/E26,"-")
A25: Phase 5: Hypercare (Wk10+HC) | B25: Wks 10–12 | C25: =SUM('Resource Plan'!K12:M12) | D25: =SUM(K13:K15) | E25: =SUM(M13:M15) | F25: =IFERROR(E25/E26,"-")
A26: TOTAL | B26: 12 wks | C26: =SUM('Resource Plan'!B12:M12) | D26: =SUM(K4:K15) | E26: =SUM(M4:M15) | F26: =IFERROR(E26/E26,"-")
