Workbook

Sheet Assumptions
A1: MAHIMA ANM PLATFORM — PROJECT ASSUMPTIONS
A2: All rates are USD per day (8-hour working day)
A3: Colour key: 🔵 Blue = hardcoded input | ⚫ Black = formula | 🟢 Green = cross-sheet reference
A5: RESOURCE RATE CARD
A6: Role | B6: Day Rate (USD) | C6: Type | D6: Notes
A7: Project Manager | B7: 900 | C7: Management | D7: Full 8-week engagement
A8: Solution Architect | B8: 1200 | C8: Technical | D8: Front-loaded Week 1–2
A9: UI/UX Designer | B9: 800 | C9: Design | D9: Phase 1–2 only
A10: Full-Stack Dev (.NET 8) | B10: 950 | C10: Development | D10: ASP.NET Core, C#, EF Core
A11: Mobile Developer | B11: 950 | C11: Development | D11: React+Capacitor, iOS build
A12: DevOps Engineer | B12: 850 | C12: Infrastructure | D12: AWS, CI/CD, Nginx
A13: QA Engineer | B13: 750 | C13: Quality | D13: Test automation + UAT
A15: PROJECT SETTINGS
A16: Parameter | B16: Value | C16: Unit | D16: Notes
A17: Implementation Weeks | B17: 8 | C17: Weeks | D17: Core delivery weeks
A18: Hypercare Weeks | B18: 2 | C18: Weeks | D18: Free post go-live support
A19: Total Project Duration | B19: =B17+B18 | C19: Weeks | D19: Implementation + Hypercare
A20: Working Days per Week | B20: 5 | C20: Days | D20: Mon–Fri
A21: Profit Margin Target | B21: 0.5 | C21: % | D21: 50% markup on cost
A22: Client Price (formula) | B22: ='Cost Model'!B14*(1+B21) | C22: USD | D22: Auto-calculated

Sheet Resource Plan
A1: RESOURCE LOADING MATRIX — 8-WEEK IMPLEMENTATION + 2-WEEK HYPERCARE
A2: Blue=input | Black=formula | HC=Hypercare | C2: ◀ IMPLEMENTATION PHASES ▶ | K2: HYPERCARE | M2: TOTALS
A3: Role | B3: Day Rate | C3: W1 | D3: W2 | E3: W3 | F3: W4 | G3: W5 | H3: W6 | I3: W7 | J3: W8 | K3: HC1 | L3: HC2 | M3: Total Days | N3: Cost (USD) | O3: Note
A4: Project Manager | B4: 900 | C4: 5 | D4: 5 | E4: 3 | F4: 2 | G4: 2 | H4: 2 | I4: 2 | J4: 3 | K4: 2 | L4: 1 | M4: =SUM(C4:L4) | N4: =B4*M4 | O4: Full-project engagement
A5: Solution Architect | B5: 1200 | C5: 4 | D5: 3 | E5: 1 | J5: 1 | M5: =SUM(C5:L5) | N5: =B5*M5 | O5: Front-loaded Weeks 1–2
A6: UI/UX Designer | B6: 800 | C6: 4 | D6: 5 | E6: 3 | F6: 1 | M6: =SUM(C6:L6) | N6: =B6*M6 | O6: Phases 1–2 only
A7: Full-Stack Dev (.NET 8) | B7: 950 | C7: 1 | D7: 2 | E7: 5 | F7: 5 | G7: 5 | H7: 3 | I7: 1 | K7: 1 | M7: =SUM(C7:L7) | N7: =B7*M7 | O7: Core customisation
A8: Mobile Developer | B8: 950 | D8: 1 | E8: 2 | F8: 3 | G8: 4 | H8: 5 | I8: 3 | J8: 1 | K8: 1 | L8: 1 | M8: =SUM(C8:L8) | N8: =B8*M8 | O8: iOS + Android Capacitor
A9: DevOps Engineer | B9: 850 | C9: 3 | D9: 2 | E9: 1 | F9: 1 | G9: 1 | H9: 1 | I9: 2 | J9: 3 | K9: 2 | L9: 1 | M9: =SUM(C9:L9) | N9: =B9*M9 | O9: AWS + CI/CD
A10: QA Engineer | B10: 750 | E10: 1 | F10: 1 | G10: 1 | H10: 1 | I10: 4 | J10: 3 | K10: 1 | L10: 1 | M10: =SUM(C10:L10) | N10: =B10*M10 | O10: QA + UAT + security
A11: TOTAL | C11: =SUM(C4:C10) | D11: =SUM(D4:D10) | E11: =SUM(E4:E10) | F11: =SUM(F4:F10) | G11: =SUM(G4:G10) | H11: =SUM(H4:H10) | I11: =SUM(I4:I10) | J11: =SUM(J4:J10) | ... N11: =SUM(N4:N10)

Sheet Cost Model
A1: MAHIMA ANM PLATFORM — COST MODEL & PRICING
A3: Line Item | B3: Amount (USD) | C3: Notes
A4: A. RESOURCE COSTS (from Resource Plan)
A5: Project Manager | B5: ='Resource Plan'!N4 | C5: Linked from Resource Plan sheet
A6: Solution Architect | B6: ='Resource Plan'!N5 | C6: Linked from Resource Plan sheet
A7: UI/UX Designer | B7: ='Resource Plan'!N6 | C7: Linked from Resource Plan sheet
A8: Full-Stack Dev (.NET 8) | B8: ='Resource Plan'!N7 | C8: Linked from Resource Plan sheet
A9: Mobile Developer | B9: ='Resource Plan'!N8 | C9: Linked from Resource Plan sheet
A10: DevOps Engineer | B10: ='Resource Plan'!N9 | C10: Linked from Resource Plan sheet
A11: QA Engineer | B11: ='Resource Plan'!N10 | C11: Linked from Resource Plan sheet
A12: RESOURCE SUB-TOTAL | B12: =SUM(B5:B11) | C12: Sum of all role costs
A13: B. PRICING BUILD-UP
A14: TOTAL COST (BASE) | B14: =B12 | C14: From resource sub-total
A15: PROFIT MARGIN (50%) | B15: =B14*Assumptions!B21 | C15: Linked from Assumptions!B21
A16: CLIENT PRICE (ONE-TIME) | B16: =B14+B15 | C16: Implementation customisation fee
A17: FREE 1-MONTH HYPERCARE | B17: 0 | C17: ~$5,000 value included at no extra cost
A19: C. YEAR 1 TOTAL COST OF OWNERSHIP
A20: One-Time Customisation | B20: =B16 | C20: Client price as above
A21: AWS Infrastructure (12 months) | B21: 1332 | C21: ~$111/month × 12
A22: Third-Party Services (12 months) | B22: 180 | C22: ~$15/month × 12
A23: AMC Pro Care (10 months from M2) | B23: =10*1500 | C23: $1,500/month × 10 months
A24: YEAR 1 TOTAL (Pro AMC) | B24: =B20+B21+B22+B23 | C24: Full first-year investment

Sheet Platform Charges
A1: MAHIMA ANM PLATFORM — MONTHLY INFRASTRUCTURE & 3RD-PARTY CHARGES
A2: Based on up to 500 ANM users · All prices USD/month estimates
A3: Service | B3: Cost/Month | C3: Annual Cost | D3: Notes
A4: ☁️ AWS INFRASTRUCTURE
A5: EC2 t3.medium (App Server) | B5: 35 | C5: =B5*12 | D5: General-purpose compute, 2vCPU 4GB RAM
A6: RDS db.t3.micro (PostgreSQL) | B6: 25 | C6: =B6*12 | D6: Managed PostgreSQL, 1vCPU 1GB RAM
A7: S3 Storage 100GB + requests | B7: 10 | C7: =B7*12 | D7: File storage for attachments + backups
A8: CloudFront CDN | B8: 8 | C8: =B8*12 | D8: Content delivery + HTTPS termination
A9: Elastic Load Balancer (ALB) | B9: 18 | C9: =B9*12 | D9: High-availability traffic distribution
A10: NAT Gateway (2 AZ) | B10: 15 | C10: =B10*12 | D10: Outbound internet for private subnets
A11: Route 53 DNS | B11: 1 | C11: =B11*12 | D11: Domain routing + health checks
A12: AWS TOTAL | B12: =SUM(B5:B11) | C12: =SUM(C5:C11) | D12: Monthly AWS infrastructure estimate
A13: 🔌 THIRD-PARTY SERVICES
A14: Twilio SMS (avg 1,000 SMS/mo) | B14: 8 | C14: =B14*12 | D14: ~$0.0079 per SMS to India
A15: Twilio Phone Number | B15: 1 | C15: =B15*12 | D15: Monthly number rental
A16: Firebase Auth (up to 50K MAU) | B16: Free | C16: $0 | D16: Free tier — no cost
A17: Email (MailKit + SMTP relay) | B17: 5 | C17: =B17*12 | D17: SendGrid free tier or Mailgun
A18: Domain Name (annual ÷ 12) | B18: 1 | C18: =B18*12 | D18: Approx ₹800–1200/year
A19: SSL Certificate (Let's Encrypt) | B19: Free | C19: $0 | D19: Free — auto-renewed via Certbot
A20: 3RD-PARTY TOTAL | B20: =SUMIF(B14:B19,">0") | C20: =B20*12 | D20: Monthly third-party estimate
A21: TOTAL MONTHLY PLATFORM COST | B21: =B12+B20 | C21: =B21*12 | D21: Annual total platform charges

Sheet AMC Plans
A1: ANNUAL MAINTENANCE & SUPPORT (AMC) PLANS — POST GO-LIVE
A2: Month 1 is FREE Hypercare (included in one-time cost). AMC billing begins Month 2.
A3: Feature / Parameter | B3: Starter Care | C3: Pro Care ★ | D3: Enterprise Care | E3: Starter Annual | F3: Pro Annual | G3: Enterprise Annual
A4: Monthly Price (USD) | B4: $800 | C4: $1,500 | D4: $2,500
A5: Annual Price (USD) | B5: $8,000 | C5: $15,000 | D5: $25,000
A6: Annual Saving vs Monthly | B6: $1,600 | C6: $3,000 | D6: $5,000
A8: Bug Fixes & Security Patches | B8: ✓ | C8: ✓ | D8: ✓
A9: OS & Dependency Updates | B9: ✓ | C9: ✓ | D9: ✓
A10: Monthly Health Report | B10: ✓ | C10: ✓ | D10: ✓
A11: Support Hours / Month | B11: 3 hrs | C11: 6 hrs | D11: 15 hrs
A12: Response SLA | B12: 48 hrs | C12: 24 hrs | D12: 4 hrs
A13: CloudWatch Monitoring Review | B13: — | C13: ✓ | D13: ✓
A14: DB Performance Tuning | B14: — | C14: ✓ | D14: ✓
A15: Minor Feature Enhancements | B15: — | C15: ✓ | D15: ✓
A16: New Feature Development | B16: — | C16: — | D16: ✓ (15hrs)
... A23: Billing Model | B23: Monthly or Annual | C23: Monthly or Annual | D23: Annual (upfront)
A25: ANNUAL CONTRACT SUMMARY
A26: Starter Care Annual | B26: 8000 | C26: Save $1,600 vs 12 months at monthly rate of $800
A27: Pro Care Annual ★ | B27: 15000 | C27: Save $3,000 vs 12 months at monthly rate of $1,500
A28: Enterprise Annual | B28: 25000 | C28: Save $5,000 vs 12 months at monthly rate of $2,500
