Workbook

Sheet Assumptions
A1: ANM Community App — Resource & Pricing Assumptions (.NET 8 + Ionic/Capacitor + PostgreSQL)
A3: Project | B3: ANM Community App
A4: Client | B4: ANM — Church & Community Platform
A5: Framework | B5: Proprietary .NET 8 + Ionic/Capacitor + PostgreSQL 16
A6: Prepared by | B6: Solution Development Team
A7: Date | B7: June 2025
A8: Currency | B8: INR (Indian Rupees — ₹)
A9: Version | B9: v2.0 — 10-Week Model
A11: RATE CARD — Daily Rates (INR) — Indian Consulting Market Rates
A12: Role | B12: Daily Rate (₹) | C12: Role ID | D12: Notes / Scope
A13: Project Manager | B13: 8500 | C13: PM | D13: Sr PM; reporting, risk, ANM stakeholder comms
A14: Solution Architect | B14: 12000 | C14: ARC | D14: Architecture reviews & formal sign-off gates
A15: UI/UX Designer | B15: 6500 | C15: DES | D15: Figma, design system, UAT design support
A16: Mobile Developer (Sr.) | B16: 9000 | C16: MOB | D16: React + Ionic/Capacitor — iOS, Android & Web via Capacitor bridges
A17: Backend Developer (Sr.) | B17: 9000 | C17: BAK | D17: ASP.NET Core .NET 8 (C#), PostgreSQL via EF Core 8, REST APIs
A18: DevOps Engineer | B18: 7500 | C18: DEV | D18: AWS ECS Fargate, RDS PostgreSQL, CI/CD, CloudFront, monitoring
A19: QA Engineer | B19: 5500 | C19: QA | D19: xUnit, Testcontainers, Playwright, Appium, OWASP testing
A20: Security Consultant | B20: 11000 | C20: SEC | D20: OWASP pentest, audit & sign-off report
A23: PRICING ASSUMPTIONS
A24: Parameter | B24: Value | D24: Notes
A25: Gross Margin % (on cost) | B25: 0.5 | D25: 50% margin added on top of total cost → client price
A26: Working Days / Week | B26: 5 | D26: Mon–Fri; excludes public holidays
A27: Hypercare Duration (weeks) | B27: 2 | D27: Post go-live monitoring & support period
A28: Sprint Length (weeks) | B28: 2 | D28: Agile: 2-week sprint cadence (5 sprints total)
A29: Project Duration — Core (wks) | B29: 10 | D29: Wk 1 through Wk 10 (Discovery → Go-Live)
A30: Total Duration incl. HC (wks) | B30: 12 | D30: Core 10 weeks + 2 hypercare weeks
A33: COLOR CODING LEGEND
A34: Blue text | B34: (sample) | D34: Hardcoded input — users may change these for scenario analysis
A35: Black text | B35: (sample) | D35: Excel formula / calculated value — do not edit manually
A36: Green text | B36: (sample) | D36: Link pulling from another worksheet within this workbook

Sheet Resource Plan
A1: ANM Community App — Resource Loading Plan (Team-Days per Week) | .NET 8 Framework — 10-Week Delivery | INR
A2: PHASE | B2: Phase 1: Discovery & Config | D2: Phase 2: Core Customisation | H2: Phase 3: Feature Completion | J2: Phase 4: QA, UAT & Launch | L2: Hypercare (Free — 30 days) | N2: TOTAL | O2: FTE | P2: Phase Focus
A3: Role | B3: Wk 1 | C3: Wk 2 | D3: Wk 3 | E3: Wk 4 | F3: Wk 5 | G3: Wk 6 | H3: Wk 7 | I3: Wk 8 | J3: Wk 9 | K3: Wk 10 | L3: HC-1 | M3: HC-2 | N3: Days | O3: ÷50d | P3: Notes
A4: Project Manager | B4: 5 | C4: 5 | D4: 3 | E4: 3 | F4: 3 | G4: 3 | H4: 3 | I4: 3 | J4: 5 | K4: 5 | L4: 2 | M4: 2 | N4: =SUM(B4:M4) | O4: =N4/50 | P4: Discovery → Go-Live → Hypercare oversight
A5: Solution Architect | B5: 5 | C5: 5 | D5: 1 | E5: 1 | G5: 1 | H5: 1 | J5: 1 | K5: 1 | N5: =SUM(B5:M5) | O5: =N5/50 | P5: Discovery & architecture; sign-off gates only
A6: UI/UX Designer | B6: 5 | C6: 5 | D6: 2 | E6: 2 | F6: 1 | G6: 1 | H6: 1 | N6: =SUM(B6:M6) | O6: =N6/50 | P6: Design-heavy Wks 1–4; wraps at Phase 2
A7: Mobile Developer (Sr.) | C7: 1 | D7: 5 | E7: 5 | F7: 5 | G7: 5 | H7: 5 | I7: 4 | J7: 3 | K7: 3 | L7: 2 | M7: 2 | N7: =SUM(B7:M7) | O7: =N7/50 | P7: Ionic/Capacitor customisation Wks 3–8; HC support
A8: Backend Developer (Sr.) | B8: 2 | C8: 2 | D8: 5 | E8: 5 | F8: 5 | G8: 5 | H8: 4 | I8: 3 | J8: 3 | K8: 3 | L8: 2 | M8: 2 | N8: =SUM(B8:M8) | O8: =N8/50 | P8: .NET 8 API Wks 1–2 design; full Wks 3–8; HC support
A9: DevOps Engineer | B9: 3 | C9: 3 | D9: 2 | E9: 2 | F9: 2 | G9: 2 | H9: 2 | I9: 2 | J9: 5 | K9: 5 | L9: 3 | M9: 3 | N9: =SUM(B9:M9) | O9: =N9/50 | P9: RDS/ECS setup Wks 1–2; prod deploy Wk9-10; HC monitoring
A10: QA Engineer | D10: 1 | E10: 1 | F10: 1 | G10: 1 | H10: 3 | I10: 4 | J10: 5 | K10: 5 | L10: 1 | M10: 1 | N10: =SUM(B10:M10) | O10: =N10/50 | P10: Engagement ramps from Wk 7; peak in QA phase Wk9-10
A11: Security Consultant | J11: 4 | K11: 3 | N11: =SUM(B11:M11) | O11: =N11/50 | P11: OWASP pentest Wk9-10 only; written report delivered
A12: TOTAL TEAM-DAYS / WEEK | B12: =SUM(B4:B11) | C12: =SUM(C4:C11) | D12: =SUM(D4:D11) | E12: =SUM(E4:E11) | F12: =SUM(F4:F11) | G12: =SUM(G4:G11) | H12: =SUM(H4:H11) | I12: =SUM(I4:I11) | ... N12: =SUM(N4:N11)
A13: Max capacity (8 roles × 5d) | B13: 40 | C13: 40 | D13: 40 | E13: 40 | F13: 40 | G13: 40 | H13: 40 | I13: 40 | J13: 40 | K13: 40 | L13: 40 | M13: 40 | N13: =SUM(B13:M13)
A14: Utilisation % | B14: =IFERROR(B12/B13,"-") | C14: =IFERROR(C12/C13,"-") | D14: =IFERROR(D12/D13,"-") | E14: =IFERROR(E12/E13,"-") | F14: =IFERROR(F12/F13,"-") | G14: =IFERROR(G12/G13,"-") | H14: =IFERROR(H12/H13,"-") | I14: =IFERROR(I12/I13,"-") | ... M14: =IFERROR(M12/M13,"-")
A16: ⚡ Framework Advantage: 10-week model vs 14-16 weeks greenfield — pre-built .NET 8 + Ionic/Capacitor modules (Auth, CRUD APIs, media pipeline, push notifs, SignalR) save ~4-6 weeks.
A18: PHASE SUMMARY
A19: Phase | B19: Weeks | C19: Team-Days | D19: % of Total | E19: Avg daily headcount | F19: Framework note
A20: Phase 1: Discovery & Config | B20: Wks 1–2 | C20: =SUM(B12:C12) | D20: =IFERROR(C20/C25,"-") | E20: =IFERROR(ROUND(C20/(2*5),1),"-") | F20: Stakeholder workshops, DB schema, Ionic scaffold, Figma
A21: Phase 2: Core Customisation | B21: Wks 3–6 | C21: =SUM(D12:G12) | D21: =IFERROR(C21/C25,"-") | E21: =IFERROR(ROUND(C21/(4*5),1),"-") | F21: Auth, Member Dir, Prayer, Video — framework modules configured
A22: Phase 3: Feature Completion | B22: Wks 7–8 | C22: =SUM(H12:I12) | D22: =IFERROR(C22/C25,"-") | E22: =IFERROR(ROUND(C22/(2*5),1),"-") | F22: Twilio Chat/VoIP, FCM push, admin RBAC, deep-link polish
A23: Phase 4: QA, UAT & Launch | B23: Wks 9–10 | C23: =SUM(J12:K12) | D23: =IFERROR(C23/C25,"-") | E23: =IFERROR(ROUND(C23/(2*5),1),"-") | F23: xUnit + Playwright + Appium + OWASP + UAT + Store submit
A24: Hypercare (Free — 30 days) | B24: HC 1–2 | C24: =SUM(L12:M12) | D24: =IFERROR(C24/C25,"-") | E24: =IFERROR(ROUND(C24/(2*5),1),"-") | F24: Free bug fixes, monitoring, admin training, handover docs
A25: TOTAL | B25: 12 wks | C25: =SUM(B12:M12) | D25: =IFERROR(C25/C25,"-") | E25: =IFERROR(ROUND(C25/(12*5),1),"-") | F25: 10 core + 2 hypercare | Framework saves ~4–6 weeks vs greenfield

Sheet Cost Model
A1: ANM Community App — Cost Build-up & Pricing Model | .NET 8 + Ionic/Capacitor + PostgreSQL | 10-Week Delivery | INR
A2: Green = cross-sheet link · Blue = editable input · Black = formula · Margin applied in rows 14–17 · All amounts in INR (₹)
A3: Role | B3: Daily Rate (₹) | C3: Project Days (Wks 1–10) | D3: HC Days (2 wks) | E3: Total Days | F3: Project Cost (₹) | G3: HC Cost (₹) | H3: Total Cost (₹) | I3: % of Total | J3: Source / Notes
A4: Project Manager | B4: =Assumptions!B13 | C4: =SUM('Resource Plan'!B4:K4) | D4: =SUM('Resource Plan'!L4:M4) | E4: =C4+D4 | F4: =B4*C4 | G4: =B4*D4 | H4: =F4+G4 | I4: =IFERROR(H4/H12,0) | J4: Rate: Assumptions!B13 | Days: Resource Plan row 4, cols B:K (core) and L:M (HC)
A5: Solution Architect | B5: =Assumptions!B14 | C5: =SUM('Resource Plan'!B5:K5) | D5: =SUM('Resource Plan'!L5:M5) | E5: =C5+D5 | F5: =B5*C5 | G5: =B5*D5 | H5: =F5+G5 | I5: =IFERROR(H5/H12,0) | J5: Rate: Assumptions!B14 | Primarily Wks 1–2; sign-off gates in Wk6 & Wk10
A6: UI/UX Designer | B6: =Assumptions!B15 | C6: =SUM('Resource Plan'!B6:K6) | D6: =SUM('Resource Plan'!L6:M6) | E6: =C6+D6 | F6: =B6*C6 | G6: =B6*D6 | H6: =F6+G6 | I6: =IFERROR(H6/H12,0) | J6: Rate: Assumptions!B15 | Design-heavy Wks 1–4; wraps by Wk7
A7: Mobile Developer (Sr.) | B7: =Assumptions!B16 | C7: =SUM('Resource Plan'!B7:K7) | D7: =SUM('Resource Plan'!L7:M7) | E7: =C7+D7 | F7: =B7*C7 | G7: =B7*D7 | H7: =F7+G7 | I7: =IFERROR(H7/H12,0) | J7: Rate: Assumptions!B16 | Ionic/Capacitor customisation Wks 3–8; HC support
A8: Backend Developer (Sr.) | B8: =Assumptions!B17 | C8: =SUM('Resource Plan'!B8:K8) | D8: =SUM('Resource Plan'!L8:M8) | E8: =C8+D8 | F8: =B8*C8 | G8: =B8*D8 | H8: =F8+G8 | I8: =IFERROR(H8/H12,0) | J8: Rate: Assumptions!B17 | ASP.NET Core .NET 8 APIs Wks 1–10; HC support
A9: DevOps Engineer | B9: =Assumptions!B18 | C9: =SUM('Resource Plan'!B9:K9) | D9: =SUM('Resource Plan'!L9:M9) | E9: =C9+D9 | F9: =B9*C9 | G9: =B9*D9 | H9: =F9+G9 | I9: =IFERROR(H9/H12,0) | J9: Rate: Assumptions!B18 | RDS/ECS setup Wks 1–2; prod deploy Wk9–10; HC monitoring
A10: QA Engineer | B10: =Assumptions!B19 | C10: =SUM('Resource Plan'!B10:K10) | D10: =SUM('Resource Plan'!L10:M10) | E10: =C10+D10 | F10: =B10*C10 | G10: =B10*D10 | H10: =F10+G10 | I10: =IFERROR(H10/H12,0) | J10: Rate: Assumptions!B19 | xUnit + Playwright + Appium; ramps from Wk7; peak Wk9–10
A11: Security Consultant | B11: =Assumptions!B20 | C11: =SUM('Resource Plan'!B11:K11) | D11: =SUM('Resource Plan'!L11:M11) | E11: =C11+D11 | F11: =B11*C11 | G11: =B11*D11 | H11: =F11+G11 | I11: =IFERROR(H11/H12,0) | J11: Rate: Assumptions!B20 | OWASP pentest Wk9–10 only; fixed scope; report delivered
A12: TOTAL COST (before margin) | C12: =SUM(C4:C11) | D12: =SUM(D4:D11) | E12: =SUM(E4:E11) | F12: =SUM(F4:F11) | G12: =SUM(G4:G11) | H12: =SUM(H4:H11) | I12: 100.0%
A14: Total Cost (₹) | H14: =H12
A15: Gross Margin % (50%) | H15: =Assumptions!B25
A16: Margin Amount (₹) | H16: =H14*H15
A17: TOTAL CLIENT PRICE (₹) | H17: =H14+H16
A18: 💡 Packages: Starter ₹32L · Standard ₹38L (Recommended) · Enterprise ₹48L | AMC: ₹15K-₹40K/mo | AWS Infra: ~₹44,825/mo (see Platform Costs sheet)
A20: COST & PRICE BY DELIVERY PHASE (10-Week + Hypercare Model)
A21: Phase | B21: Weeks | C21: Team-Days | D21: Proportional Cost (₹) | E21: Selling Price incl. 50% Margin | F21: % of Total Price
A22: Phase 1: Discovery & Config | B22: Wks 1–2 | C22: =SUM('Resource Plan'!B12:C12) | D22: =IFERROR(C22/E12*H12,0) | E22: =IFERROR(D22*(1+Assumptions!B25),0) | F22: =IFERROR(E22/H17,"-")
A23: Phase 2: Core Customisation | B23: Wks 3–6 | C23: =SUM('Resource Plan'!D12:G12) | D23: =IFERROR(C23/E12*H12,0) | E23: =IFERROR(D23*(1+Assumptions!B25),0) | F23: =IFERROR(E23/H17,"-")
A24: Phase 3: Feature Completion | B24: Wks 7–8 | C24: =SUM('Resource Plan'!H12:I12) | D24: =IFERROR(C24/E12*H12,0) | E24: =IFERROR(D24*(1+Assumptions!B25),0) | F24: =IFERROR(E24/H17,"-")
A25: Phase 4: QA, UAT & Launch | B25: Wks 9–10 | C25: =SUM('Resource Plan'!J12:K12) | D25: =IFERROR(C25/E12*H12,0) | E25: =IFERROR(D25*(1+Assumptions!B25),0) | F25: =IFERROR(E25/H17,"-")
A26: Hypercare (Free — 30 days) | B26: HC 1–2 | C26: =SUM('Resource Plan'!L12:M12) | D26: =IFERROR(C26/E12*H12,0) | E26: =IFERROR(D26*(1+Assumptions!B25),0) | F26: =IFERROR(E26/H17,"-")
A27: TOTAL | B27: 12 wks | C27: =E12 | D27: =IFERROR(C27/E12*H12,0) | E27: =IFERROR(D27*(1+Assumptions!B25),0) | F27: =IFERROR(E27/H17,"-")

Sheet Weekly Cost
A1: ANM Community App — Weekly Cost Breakdown & Cash Flow | .NET 8 Framework | 10-Week Delivery | INR
A2: Costs = days (Resource Plan) × rate (Assumptions) · Selling price = cost × (1 + 50% margin) · All amounts in INR (₹) · 12 weeks total incl. 2 hypercare
A3: Week | B3: Phase | C3: PM | D3: Architect | E3: Designer | F3: Mobile Dev (Ionic/Cap) | G3: Backend Dev (.NET 8) | H3: DevOps (RDS/ECS) | I3: QA Eng | J3: Security | K3: Total Cost /Wk (₹) | L3: Cumul. Cost (₹) | M3: Sell Price /Wk (₹) | N3: Cumul. Sell Price (₹)
A4: Wk 1 | B4: Phase 1: Discovery & Config | C4: ='Resource Plan'!B4*Assumptions!B13 | D4: ='Resource Plan'!B5*Assumptions!B14 | E4: ='Resource Plan'!B6*Assumptions!B15 | F4: ='Resource Plan'!B7*Assumptions!B16 | G4: ='Resource Plan'!B8*Assumptions!B17 | H4: ='Resource Plan'!B9*Assumptions!B18 | I4: ='Resource Plan'!B10*Assumptions!B19 | J4: ='Resource Plan'!B11*Assumptions!B20 | K4: =SUM(C4:J4) | L4: =K4 | M4: =K4*(1+Assumptions!B25) | N4: =M4
A5: Wk 2 | B5: Phase 1: Discovery & Config | C5: ='Resource Plan'!C4*Assumptions!B13 | D5: ='Resource Plan'!C5*Assumptions!B14 | E5: ='Resource Plan'!C6*Assumptions!B15 | F5: ='Resource Plan'!C7*Assumptions!B16 | G5: ='Resource Plan'!C8*Assumptions!B17 | H5: ='Resource Plan'!C9*Assumptions!B18 | I5: ='Resource Plan'!C10*Assumptions!B19 | J5: ='Resource Plan'!C11*Assumptions!B20 | K5: =SUM(C5:J5) | L5: =L4+K5 | M5: =K5*(1+Assumptions!B25) | N5: =N4+M5
A6: Wk 3 | B6: Phase 2: Core Customisation | C6: ='Resource Plan'!D4*Assumptions!B13 | D6: ='Resource Plan'!D5*Assumptions!B14 | E6: ='Resource Plan'!D6*Assumptions!B15 | F6: ='Resource Plan'!D7*Assumptions!B16 | G6: ='Resource Plan'!D8*Assumptions!B17 | H6: ='Resource Plan'!D9*Assumptions!B18 | I6: ='Resource Plan'!D10*Assumptions!B19 | J6: ='Resource Plan'!D11*Assumptions!B20 | K6: =SUM(C6:J6) | L6: =L5+K6 | M6: =K6*(1+Assumptions!B25) | N6: =N5+M6
A7: Wk 4 | B7: Phase 2: Core Customisation | C7: ='Resource Plan'!E4*Assumptions!B13 | D7: ='Resource Plan'!E5*Assumptions!B14 | E7: ='Resource Plan'!E6*Assumptions!B15 | F7: ='Resource Plan'!E7*Assumptions!B16 | G7: ='Resource Plan'!E8*Assumptions!B17 | H7: ='Resource Plan'!E9*Assumptions!B18 | I7: ='Resource Plan'!E10*Assumptions!B19 | J7: ='Resource Plan'!E11*Assumptions!B20 | K7: =SUM(C7:J7) | L7: =L6+K7 | M7: =K7*(1+Assumptions!B25) | N7: =N6+M7
A8: Wk 5 | B8: Phase 2: Core Customisation | C8: ='Resource Plan'!F4*Assumptions!B13 | D8: ='Resource Plan'!F5*Assumptions!B14 | E8: ='Resource Plan'!F6*Assumptions!B15 | F8: ='Resource Plan'!F7*Assumptions!B16 | G8: ='Resource Plan'!F8*Assumptions!B17 | H8: ='Resource Plan'!F9*Assumptions!B18 | I8: ='Resource Plan'!F10*Assumptions!B19 | J8: ='Resource Plan'!F11*Assumptions!B20 | K8: =SUM(C8:J8) | L8: =L7+K8 | M8: =K8*(1+Assumptions!B25) | N8: =N7+M8
A9: Wk 6 | B9: Phase 2: Core Customisation | C9: ='Resource Plan'!G4*Assumptions!B13 | D9: ='Resource Plan'!G5*Assumptions!B14 | E9: ='Resource Plan'!G6*Assumptions!B15 | F9: ='Resource Plan'!G7*Assumptions!B16 | G9: ='Resource Plan'!G8*Assumptions!B17 | H9: ='Resource Plan'!G9*Assumptions!B18 | I9: ='Resource Plan'!G10*Assumptions!B19 | J9: ='Resource Plan'!G11*Assumptions!B20 | K9: =SUM(C9:J9) | L9: =L8+K9 | M9: =K9*(1+Assumptions!B25) | N9: =N8+M9
A10: Wk 7 | B10: Phase 3: Feature Completion | C10: ='Resource Plan'!H4*Assumptions!B13 | D10: ='Resource Plan'!H5*Assumptions!B14 | E10: ='Resource Plan'!H6*Assumptions!B15 | F10: ='Resource Plan'!H7*Assumptions!B16 | G10: ='Resource Plan'!H8*Assumptions!B17 | H10: ='Resource Plan'!H9*Assumptions!B18 | I10: ='Resource Plan'!H10*Assumptions!B19 | J10: ='Resource Plan'!H11*Assumptions!B20 | K10: =SUM(C10:J10) | L10: =L9+K10 | M10: =K10*(1+Assumptions!B25) | N10: =N9+M10
A11: Wk 8 | B11: Phase 3: Feature Completion | C11: ='Resource Plan'!I4*Assumptions!B13 | D11: ='Resource Plan'!I5*Assumptions!B14 | E11: ='Resource Plan'!I6*Assumptions!B15 | F11: ='Resource Plan'!I7*Assumptions!B16 | G11: ='Resource Plan'!I8*Assumptions!B17 | H11: ='Resource Plan'!I9*Assumptions!B18 | I11: ='Resource Plan'!I10*Assumptions!B19 | J11: ='Resource Plan'!I11*Assumptions!B20 | K11: =SUM(C11:J11) | L11: =L10+K11 | M11: =K11*(1+Assumptions!B25) | N11: =N10+M11
A12: Wk 9 | B12: Phase 4: QA, UAT & Launch | C12: ='Resource Plan'!J4*Assumptions!B13 | D12: ='Resource Plan'!J5*Assumptions!B14 | E12: ='Resource Plan'!J6*Assumptions!B15 | F12: ='Resource Plan'!J7*Assumptions!B16 | G12: ='Resource Plan'!J8*Assumptions!B17 | H12: ='Resource Plan'!J9*Assumptions!B18 | I12: ='Resource Plan'!J10*Assumptions!B19 | J12: ='Resource Plan'!J11*Assumptions!B20 | K12: =SUM(C12:J12) | L12: =L11+K12 | M12: =K12*(1+Assumptions!B25) | N12: =N11+M12
A13: Wk 10 | B13: Phase 4: QA, UAT & Launch | C13: ='Resource Plan'!K4*Assumptions!B13 | D13: ='Resource Plan'!K5*Assumptions!B14 | E13: ='Resource Plan'!K6*Assumptions!B15 | F13: ='Resource Plan'!K7*Assumptions!B16 | G13: ='Resource Plan'!K8*Assumptions!B17 | H13: ='Resource Plan'!K9*Assumptions!B18 | I13: ='Resource Plan'!K10*Assumptions!B19 | J13: ='Resource Plan'!K11*Assumptions!B20 | K13: =SUM(C13:J13) | L13: =L12+K13 | M13: =K13*(1+Assumptions!B25) | N13: =N12+M13
A14: HC-Wk1 | B14: Hypercare (Free — 30 days) | C14: ='Resource Plan'!L4*Assumptions!B13 | D14: ='Resource Plan'!L5*Assumptions!B14 | E14: ='Resource Plan'!L6*Assumptions!B15 | F14: ='Resource Plan'!L7*Assumptions!B16 | G14: ='Resource Plan'!L8*Assumptions!B17 | H14: ='Resource Plan'!L9*Assumptions!B18 | I14: ='Resource Plan'!L10*Assumptions!B19 | J14: ='Resource Plan'!L11*Assumptions!B20 | K14: =SUM(C14:J14) | L14: =L13+K14 | M14: =K14*(1+Assumptions!B25) | N14: =N13+M14
A15: HC-Wk2 | B15: Hypercare (Free — 30 days) | C15: ='Resource Plan'!M4*Assumptions!B13 | D15: ='Resource Plan'!M5*Assumptions!B14 | E15: ='Resource Plan'!M6*Assumptions!B15 | F15: ='Resource Plan'!M7*Assumptions!B16 | G15: ='Resource Plan'!M8*Assumptions!B17 | H15: ='Resource Plan'!M9*Assumptions!B18 | I15: ='Resource Plan'!M10*Assumptions!B19 | J15: ='Resource Plan'!M11*Assumptions!B20 | K15: =SUM(C15:J15) | L15: =L14+K15 | M15: =K15*(1+Assumptions!B25) | N15: =N14+M15
A16: TOTAL | C16: =SUM(C4:C15) | D16: =SUM(D4:D15) | E16: =SUM(E4:E15) | F16: =SUM(F4:F15) | G16: =SUM(G4:G15) | H16: =SUM(H4:H15) | I16: =SUM(I4:I15) | J16: =SUM(J4:J15) | K16: =SUM(K4:K15) | L16: =L15 | M16: =SUM(M4:M15) | N16: =N15
A18: COST SUMMARY BY PHASE (10-Week + Hypercare Model)
A19: Phase | B19: Weeks | C19: Team-Days | D19: Cost (₹) | E19: Selling Price (₹) | F19: % of Total
A20: Phase 1: Discovery & Config | B20: Wks 1–2 | C20: =SUM('Resource Plan'!B12:C12) | D20: =SUM(K4:K5) | E20: =SUM(M4:M5) | F20: =IFERROR(E20/E25,"-")
A21: Phase 2: Core Customisation | B21: Wks 3–6 | C21: =SUM('Resource Plan'!D12:G12) | D21: =SUM(K6:K9) | E21: =SUM(M6:M9) | F21: =IFERROR(E21/E25,"-")
A22: Phase 3: Feature Completion | B22: Wks 7–8 | C22: =SUM('Resource Plan'!H12:I12) | D22: =SUM(K10:K11) | E22: =SUM(M10:M11) | F22: =IFERROR(E22/E25,"-")
A23: Phase 4: QA, UAT & Launch | B23: Wks 9–10 | C23: =SUM('Resource Plan'!J12:K12) | D23: =SUM(K12:K13) | E23: =SUM(M12:M13) | F23: =IFERROR(E23/E25,"-")
A24: Hypercare (Free — 30 days) | B24: HC 1–2 | C24: =SUM('Resource Plan'!L12:M12) | D24: =SUM(K14:K15) | E24: =SUM(M14:M15) | F24: =IFERROR(E24/E25,"-")
A25: TOTAL | B25: 12 wks | C25: =SUM('Resource Plan'!B12:M12) | D25: =SUM(K4:K15) | E25: =SUM(M4:M15) | F25: =IFERROR(E25/E25,"-")

Sheet AMC Options
A1: ANM Community App — Annual Maintenance Contract (AMC) Options | Post Go-Live | INR
A2: Choose an AMC tier based on desired SLA, feature development needs, and budget. AMC pricing is per month and billed quarterly.
A4: Feature / Parameter | B4: Basic | C4: ⭐ Standard (Recommended) | D4: Premium | E4: Notes
A5: Monthly Price (₹) | B5: 15000 | C5: 25000 | D5: 40000 | E5: Billed quarterly in advance
A6: Annual Cost (₹) | B6: =B5*12 | C6: =C5*12 | D6: =D5*12
A8: Bug Fixes & Patches | B8: Included | C8: Included | D8: Included | E8: OS & device compatibility + security patches
A9: Monthly Health Check Report | B9: Included | C9: Included | D9: Included | E9: Performance, uptime, DB metrics report
A10: Response SLA | B10: 48 hours | C10: 8 hours | D10: 2 hours | E10: From ticket raised to first response
A11: Resolution SLA (critical bugs) | B11: 5 business days | C11: 2 business days | D11: Next business day | E11: P1 critical issue resolution
A12: Minor UI/UX Enhancements | B12: – | C12: 2 per quarter | D12: Unlimited* | E12: *Subject to 4h/month cap for Standard
A13: Feature Development (hours/mo) | B13: 0 hours | C13: 8 hours | D13: 20 hours | E13: Pre-agreed scope; billed additionally beyond cap
A14: AWS Cost Optimisation Review | B14: – | C14: Quarterly | D14: Monthly | E14: RDS, ECS, S3 cost right-sizing
A15: Dedicated Support Manager | B15: – | C15: – | D15: Included | E15: Named contact for all support escalations
A16: Priority Queue | B16: – | C16: Yes | D16: Yes (highest) | E16: Tickets prioritised above non-AMC clients
A17: App Store Update Submissions | B17: 1 per quarter | C17: 2 per quarter | D17: Unlimited | E17: Binary + metadata updates to Apple & Google
A18: Database Backup Verification | B18: Monthly | C18: Weekly | D18: Daily | E18: RDS automated backup restore test
A19: Uptime SLA | B19: – | C19: 99.5% | D19: 99.9% | E19: Based on AWS CloudWatch metrics
... A21: Phase 2 Feature Backlog Grooming | B21: – | C21: – | D21: Included | E21: Monthly 1h session to refine enhancement backlog
A24: ⚠️ AMC begins after the 30-day free Hypercare period. All AMC tiers include Twilio & Firebase config updates. AWS costs are pass-through (billed separately).

Sheet Platform Costs
A1: ANM Community App — Monthly Platform & Infrastructure Costs | Client-Borne | INR
A2: These costs are client-borne and billed directly by AWS / Twilio / Firebase. They are OVER AND ABOVE the implementation fee. Exchange rate basis: 1 USD ≈ ₹84. Sized for 100,000 church members.
A4: AWS — Compute & Database
A5: Service / Resource | B5: Cost Low (₹) | C5: Cost High (₹) | D5: Frequency | E5: Notes
A6: AWS RDS PostgreSQL 16 (db.r6g.large, Multi-AZ, 500 GB gp3) | B6: 30000 | C6: 30000 | D6: Monthly | E6: Upgraded from t4g.medium — 2 vCPU, 16 GB RAM required at 100K member scale
A7: AWS ECS Fargate (4 baseline tasks / 2 vCPU / 4 GB, scales to 15) | B7: 28000 | C7: 45000 | D7: Monthly | E7: .NET 8 containers; auto-scale 4–15 tasks; avg 5–8 tasks in practice
A8: AWS S3 + CloudFront CDN (1 TB storage + 3–7 TB egress/mo) | B8: 20000 | C8: 40000 | D8: Monthly | E8: Video library; 100K members watching sermons = 3–7 TB CDN egress/mo
A9: AWS CloudWatch + X-Ray (metrics, traces, logs) | B9: 3500 | C9: 5000 | D9: Monthly | E9: Monitoring, alerting, distributed tracing — higher volume at 100K scale
A10: AWS ALB + WAF (managed rule groups, ~10M req/mo) | B10: 4500 | C10: 6000 | D10: Monthly | E10: WAF managed rules ($20/mo extra) + more LCUs at higher traffic
A11: AWS Route 53 (DNS hosting + health checks) | B11: 500 | C11: 500 | D11: Monthly | E11: SSL via ACM (free) + DNS zone + health check routing
A12: AWS ElastiCache Redis (cache.t3.small, 2-node HA cluster) | B12: 4200 | C12: 4200 | D12: Monthly | E12: NEW at 100K — session cache, query cache, rate-limit counters; essential for performance
A13: AWS NAT Gateway (private subnet for ECS tasks) | B13: 3000 | C13: 4500 | D13: Monthly | E13: NEW — required for ECS in private VPC subnet; ~50–100 GB data processed/mo
A14: AWS SES (transactional email, est. 50,000 msgs/mo) | B14: 500 | C14: 800 | D14: Monthly | E14: Welcome, digest, alerts — $0.10/1,000 emails via SES
A16: Twilio — Communications
A17: Service / Resource | B17: Cost Low (₹) | C17: Cost High (₹) | D17: Frequency | E17: Notes
A18: Twilio Voice (in-app VoIP, est. 2,000–5,000 mins/mo) | B18: 8400 | C18: 21000 | D18: Monthly | E18: ~₹4.2/min; scales with call adoption. 2K min low / 5K min high
A19: Twilio SMS (OTP + notifications, est. 1,500–3,000 msgs/mo) | B19: 7350 | C19: 14700 | D19: Monthly | E19: ~₹4.9/SMS; India DLT registered; 1,500 low / 3,000 high msgs/mo
A20: ⚠️ Twilio Conversations (Chat SDK — 10K–20K active MAU) | B20: 42000 | C20: 84000 | D20: Monthly | E20: CRITICAL: $0.05/active chat user/mo. 10% adoption=10K MAU=₹42K; 20%=₹84K. See Scale Scenarios sheet for alternative.
A22: Firebase — Auth & Notifications
A23: Service / Resource | B23: Cost Low (₹) | C23: Cost High (₹) | D23: Frequency | E23: Notes
A24: Firebase Auth (email/password + Google OAuth) | B24: Free | C24: Free | D24: Free | E24: Email/password & Google OAuth: free at any scale — no per-user cost
A25: Firebase Auth (phone OTP — new signups only, ~1,000/mo) | B25: 504 | C25: 1008 | D25: Monthly | E25: $0.006/SMS verification; only new monthly sign-ups trigger this cost
A26: Firebase FCM Push Notifications | B26: Free | C26: Free | D26: Free | E26: Unlimited push notifications — no cost regardless of scale
A27: Firebase Hosting (PWA served via CloudFront origin shield) | B27: Free | C27: Free | D27: Free | E27: CloudFront absorbs egress; Firebase serves minimal traffic to CDN origin
A29: App Stores & Third-Party
A30: Service / Resource | B30: Cost Low (₹) | C30: Cost High (₹) | D30: Frequency | E30: Notes
A31: Apple Developer Program (annual — amortised monthly) | B31: 692 | C31: 692 | D31: Monthly | E31: ₹8,299/yr ÷ 12 = ₹692/mo shown here; billed annually by Apple
A32: Google Play Console (one-time registration) | B32: 2500 | C32: 2500 | D32: One-time | E32: ₹2,500 one-time; no annual fee
A33: Twilio DLT Registration (India TRAI — one-time) | B33: 7500 | C33: 10000 | D33: One-time | E33: Required for transactional SMS in India; process takes 1–2 weeks
A35: ESTIMATED TOTAL MONTHLY PLATFORM COST | B35: =B6+B7+B8+B9+B10+B11+B12+B13+B14+B18+B19+B20+B25+B31 | C35: =C6+C7+C8+C9+C10+C11+C12+C13+C14+C18+C19+C20+C25+C31 | D35: Monthly | E35: Monthly recurring only. Excl. one-time fees (Google Play ₹2,500 + Twilio DLT ₹7,500–10,000) + Apple Dev ₹692/mo amortised. See Scale Scenarios sheet.
A37: 💡 Sized for 100,000 church members (Low = ~15–20% MAU active; High = ~35–40% MAU active). ⚠️ Twilio Conversations at ₹42K–84K/mo is the #1 cost driver — see Scale Scenarios sheet for SignalR alternative (saves ₹42K–84K/mo). AWS costs vary with usage; review quarterly.

Sheet Scale Scenarios
A1: ANM Community App — Monthly Platform Cost: Scale Scenarios Comparison | INR
A2: Exchange rate: 1 USD ≈ ₹84 | Low = conservative MAU activity | High = peak MAU activity | ⚠️ Twilio Conversations = $0.05/active chat user/month
A4: Service / Cost Driver | B4: 500–1K Users Low (₹) | C4: 500–1K Users High (₹) | D4: 100K Users Low (₹) | E4: 100K Users High (₹) | F4: Notes
A6: AWS — COMPUTE & DATABASE
A7: RDS PostgreSQL | B7: 18500 | C7: 18500 | D7: 30000 | E7: 30000 | F7: Upgraded: t4g.medium → r6g.large + 500 GB storage at 100K scale
A8: ECS Fargate | B8: 12000 | C8: 12000 | D8: 28000 | E8: 45000 | F8: 4–15 tasks (2 vCPU/4 GB) vs 2 tasks (1 vCPU/2 GB) at small scale
A9: S3 + CloudFront CDN | B9: 6000 | C9: 6000 | D9: 20000 | E9: 40000 | F9: 3–7 TB CDN egress at 100K vs 1 TB at small scale
A10: CloudWatch + X-Ray | B10: 1500 | C10: 1500 | D10: 3500 | E10: 5000 | F10: Higher log volume and trace data at 100K
A11: ALB + WAF | B11: 2000 | C11: 2000 | D11: 4500 | E11: 6000 | F11: WAF managed rules added at 100K; more LCUs
A12: Route 53 | B12: 500 | C12: 500 | D12: 500 | E12: 500 | F12: Unchanged
A13: ElastiCache Redis | B13: – | C13: – | D13: 4200 | E13: 4200 | F13: NEW at 100K — caching essential for performance at scale
A14: NAT Gateway | B14: – | C14: – | D14: 3000 | E14: 4500 | F14: NEW at 100K — required for ECS in private VPC subnet
A15: AWS SES (email) | B15: 800 | C15: 800 | D15: 500 | E15: 800 | F15: Scaled email volume; SES replaces SendGrid at 100K
A16: AWS Subtotal | B16: 41300 | C16: 41300 | D16: 94200 | E16: 136000 | F16: 8 services at 500-1K scale → 9 services at 100K
A17: TWILIO — COMMUNICATIONS
A18: Twilio Voice (VoIP) | B18: 2100 | C18: 2100 | D18: 8400 | E18: 21000 | F18: 2K–5K min/mo at 100K vs 500 min/mo at small scale
A19: Twilio SMS (OTP) | B19: 1225 | C19: 1225 | D19: 7350 | E19: 14700 | F19: 1.5K–3K msgs/mo at 100K vs 250 at small scale
A20: ⚠️ Twilio Conversations | B20: 1500 | C20: 1500 | D20: 42000 | E20: 84000 | F20: ⚠️ CRITICAL: $0.05/MAU. 10K MAU=₹42K; 20K MAU=₹84K. Biggest cost driver at 100K
A21: Twilio Subtotal | B21: 4825 | C21: 4825 | D21: 57750 | E21: 119700 | F21: Twilio Conversations dominates at scale
A22: FIREBASE — AUTH & NOTIFICATIONS
A23: Firebase Auth (email/Google) | B23: Free | C23: Free | D23: Free | E23: Free | F23: Free at any scale for email/password + Google OAuth
A24: Firebase Auth (phone OTP) | B24: Free | C24: Free | D24: 504 | E24: 1008 | F24: New at 100K — ~1,000 phone OTP verifications/mo for new signups
A25: Firebase FCM (push) | B25: Free | C25: Free | D25: Free | E25: Free | F25: Free at any scale — unlimited push notifications
A26: Firebase Subtotal | B26: 0 | C26: 0 | D26: 504 | E26: 1008 | F26: Essentially free even at 100K if using email/Google auth
A27: SCENARIO A — WITH Twilio Conversations
A28: Total Monthly (with Twilio Chat) | B28: 46125 | C28: 46125 | D28: 152454 | E28: 256708 | F28: Full Twilio stack — Conversations SDK for in-app chat
A29: SCENARIO B — WITHOUT Twilio Conversations (SignalR + PostgreSQL)
A30: SignalR + PostgreSQL Chat | B30: Free | C30: Free | D30: Free | E30: Free | F30: Built into .NET 8 + existing RDS — zero additional monthly cost
A31: Total Monthly (SignalR chat) | B31: 44625 | C31: 44625 | D31: 110454 | E31: 172708 | F31: Recommended at 100K — saves ₹42K–84K/mo vs Twilio Conversations
A32: Monthly Saving vs Scenario A | B32: 1500 | C32: 1500 | D32: 42000 | E32: 84000 | F32: Switch from Twilio Conversations to SignalR saves this amount per month
A33: Annual Saving vs Scenario A | B33: 18000 | C33: 18000 | D33: 504000 | E33: 1008000 | F33: ₹5.04 lakh – ₹10.08 lakh per year saved by using SignalR for chat
A35: ✅ RECOMMENDATION: Use SignalR + PostgreSQL for member-to-member chat (already in your .NET 8 stack — zero extra cost). Reserve Twilio for VoIP calls + SMS OTP only. At 100K members this saves ₹42,000–₹84,000 per month (₹5–10 lakh/year). Twilio Conversations only makes sense if you need cross-platform chat history, typing indicators, and rich media outside the app context.
A37: ⚠️ AWS cost grows ~3.5× from 500-1K to 100K members due to: larger RDS instance class, more ECS tasks, significantly higher CloudFront egress, and two new mandatory services (ElastiCache + NAT Gateway). All costs are estimates; review quarterly and right-size as user base is confirmed.
